txt_counter.py
txt_counter-0.1.0.dist-info/METADATA
txt_counter-0.1.0.dist-info/WHEEL
txt_counter-0.1.0.dist-info/top_level.txt
txt_counter-0.1.0.dist-info/RECORD
